valetudo_map_parser/__init__.py
valetudo_map_parser/config/__init__.py
valetudo_map_parser/config/async_utils.py
valetudo_map_parser/config/colors.py
valetudo_map_parser/config/drawable.py
valetudo_map_parser/config/drawable_elements.py
valetudo_map_parser/config/fonts/FiraSans.ttf
valetudo_map_parser/config/fonts/Inter-VF.ttf
valetudo_map_parser/config/fonts/Lato-Regular.ttf
valetudo_map_parser/config/fonts/MPLUSRegular.ttf
valetudo_map_parser/config/fonts/NotoKufiArabic-VF.ttf
valetudo_map_parser/config/fonts/NotoSansCJKhk-VF.ttf
valetudo_map_parser/config/fonts/NotoSansKhojki.ttf
valetudo_map_parser/config/material.py
valetudo_map_parser/config/optimized_element_map.py
valetudo_map_parser/config/rand256_parser.py
valetudo_map_parser/config/shared.py
valetudo_map_parser/config/status_text/__init__.py
valetudo_map_parser/config/status_text/status_text.py
valetudo_map_parser/config/status_text/translations.py
valetudo_map_parser/config/types.py
valetudo_map_parser/config/utils.py
valetudo_map_parser/const.py
valetudo_map_parser/hypfer_draw.py
valetudo_map_parser/hypfer_handler.py
valetudo_map_parser/map_data.py
valetudo_map_parser/py.typed
valetudo_map_parser/rand256_handler.py
valetudo_map_parser/reimg_draw.py
valetudo_map_parser/rooms_handler.py
valetudo_map_parser-0.2.1.dist-info/METADATA
valetudo_map_parser-0.2.1.dist-info/WHEEL
valetudo_map_parser-0.2.1.dist-info/licenses/LICENSE
valetudo_map_parser-0.2.1.dist-info/licenses/NOTICE.txt
valetudo_map_parser-0.2.1.dist-info/RECORD
