Metadata-Version: 2.4
Name: valetudo-map-parser
Version: 0.2.1
Summary: A Python library to parse Valetudo map data returning a PIL Image object.
License: Apache-2.0
License-File: LICENSE
License-File: NOTICE.txt
Author: Sandro Cantarella
Author-email: gsca075@gmail.com
Requires-Python: >=3.13
Classifier: License :: OSI Approved :: Apache Software License
Classifier: Programming Language :: Python :: 3
Classifier: Programming Language :: Python :: 3.13
Classifier: Programming Language :: Python :: 3.14
Requires-Dist: Pillow (>=10.3.0)
Requires-Dist: mvcrender (==0.0.8)
Requires-Dist: numpy (>=1.26.4)
Requires-Dist: scipy (>=1.12.0)
Project-URL: Bug Tracker, https://github.com/sca075/Python-package-valetudo-map-parser/issues
Project-URL: Changelog, https://github.com/sca075/Python-package-valetudo-map-parser/releases
Project-URL: Homepage, https://github.com/sca075/Python-package-valetudo-map-parser
Project-URL: Repository, https://github.com/sca075/Python-package-valetudo-map-parser
